topsis/__init__.py
topsis/__main__.py
Topsis_Khushboo_102103049-1.0.0.dist-info/LICENSE
Topsis_Khushboo_102103049-1.0.0.dist-info/METADATA
Topsis_Khushboo_102103049-1.0.0.dist-info/WHEEL
Topsis_Khushboo_102103049-1.0.0.dist-info/entry_points.txt
Topsis_Khushboo_102103049-1.0.0.dist-info/top_level.txt
Topsis_Khushboo_102103049-1.0.0.dist-info/RECORD
